agent_lite/__init__.py
agent_lite/composition.py
agent_lite/context.py
agent_lite/link.py
agent_lite/logger.py
agent_lite/model.py
agent_lite/output_parser.py
agent_lite/prompt.py
agent_lite/tool.py
agent_lite-0.1.2.dist-info/METADATA
agent_lite-0.1.2.dist-info/WHEEL
agent_lite-0.1.2.dist-info/RECORD
