Metadata-Version: 2.1
Name: agent-lite
Version: 0.1.2
Summary: 
Author: Elliot Kang
Author-email: you@example.com
Requires-Python: >=3.7
Classifier: Programming Language :: Python :: 3
Classifier: Programming Language :: Python :: 3.7
Classifier: Programming Language :: Python :: 3.8
Classifier: Programming Language :: Python :: 3.9
Classifier: Programming Language :: Python :: 3.10
Classifier: Programming Language :: Python :: 3.11
Classifier: Programming Language :: Python :: 3.12
Requires-Dist: aiohttp (>=3.6.0)
Requires-Dist: asyncio (>=3.0.0)
Requires-Dist: pydantic (>=2)
